Metadata-Version: 2.1
Name: pyuuidapikey
Version: 0.0.3
Summary: A Simple package to generate and validate UUID and API key pairs
Home-page: https://github.com/kumaF/py-uuid-apikey
Author: Kumara Fernando
Author-email: mklmfernando@gmail.com
License: UNKNOWN
Platform: UNKNOWN
Classifier: Programming Language :: Python :: 3
Classifier: License :: OSI Approved :: MIT License
Classifier: Operating System :: OS Independent
Requires-Python: >=3.6
License-File: LICENSE
